allspeak/__init__.py
allspeak/allspeak.py
allspeak/i18n.py
allspeak/integrations.py
allspeak/l10n.py
allspeak/reader.py
allspeak/request_manager.py
allspeak/utils.py
allspeak/version.py
allspeak-1.4.2.dist-info/LICENSE.txt
allspeak-1.4.2.dist-info/METADATA
allspeak-1.4.2.dist-info/WHEEL
allspeak-1.4.2.dist-info/top_level.txt
allspeak-1.4.2.dist-info/RECORD
