Metadata-Version: 2.1
Name: allspeak
Version: 1.4.2
Summary: A pythonic internationalization and localization solution.
Home-page: https://jpscaletti.com/allspeak
Author: Juan-Pablo Scaletti
Author-email: juanpablo@jpscaletti.com
License: MIT
Project-URL: Documentation, http://allspeak.lucuma.co
Platform: UNKNOWN
Classifier: Development Status :: 5 - Production/Stable
Classifier: Intended Audience :: Developers
Classifier: License :: OSI Approved :: MIT License
Classifier: Programming Language :: Python :: 3
Requires-Python: >=3.5,<4.0
Requires-Dist: Babel (~=2.7.0)
Requires-Dist: MarkupSafe (~=1.1.1)
Requires-Dist: poyo (~=0.4.2)
Requires-Dist: pytz (>=2019.1)
Provides-Extra: dev
Requires-Dist: django ; extra == 'dev'
Requires-Dist: jinja2 ; extra == 'dev'
Requires-Dist: pytest ; extra == 'dev'
Requires-Dist: webob ; extra == 'dev'
Requires-Dist: werkzeug ; extra == 'dev'
Requires-Dist: flake8 ; extra == 'dev'
Requires-Dist: ipdb ; extra == 'dev'
Requires-Dist: pytest-cov ; extra == 'dev'
Requires-Dist: sphinx ; extra == 'dev'
Requires-Dist: tox ; extra == 'dev'
Provides-Extra: testing
Requires-Dist: django ; extra == 'testing'
Requires-Dist: jinja2 ; extra == 'testing'
Requires-Dist: pytest ; extra == 'testing'
Requires-Dist: webob ; extra == 'testing'
Requires-Dist: werkzeug ; extra == 'testing'
